{
  "accentColor": "{{appsmith.theme.colors.primaryColor}}",
  "animateLoading": true,
  "borderColor": "#E0DEDE",
  "borderRadius": "0.375rem",
  "borderWidth": "1",
  "bottomRow": 54,
  "boxShadow": "0 1px 3px 0 rgba(0, 0, 0, 0.1), 0 1px 2px 0 rgba(0, 0, 0, 0.06)",
  "canFreezeColumn": false,
  "childStylesheet": {
    "button": {
      "borderRadius": "{{appsmith.theme.borderRadius.appBorderRadius}}",
      "boxShadow": "none",
      "buttonColor": "{{appsmith.theme.colors.primaryColor}}"
    },
    "editActions": {
      "discardBorderRadius": "{{appsmith.theme.borderRadius.appBorderRadius}}",
      "discardButtonColor": "{{appsmith.theme.colors.primaryColor}}",
      "saveBorderRadius": "{{appsmith.theme.borderRadius.appBorderRadius}}",
      "saveButtonColor": "{{appsmith.theme.colors.primaryColor}}"
    },
    "iconButton": {
      "borderRadius": "{{appsmith.theme.borderRadius.appBorderRadius}}",
      "boxShadow": "none",
      "buttonColor": "{{appsmith.theme.colors.primaryColor}}"
    },
    "menuButton": {
      "borderRadius": "{{appsmith.theme.borderRadius.appBorderRadius}}",
      "boxShadow": "none",
      "menuColor": "{{appsmith.theme.colors.primaryColor}}"
    }
  },
  "columnOrder": [
    "rowIndex",
    "xn__eqr1se2n6x9a",
    "xn__zwqw83l",
    "xn__zwq77g4sizzmcm7b",
    "xn__zwqu88acr6akcab",
    "xn__4kq52bt28ik8j",
    "xn__4kq52bf4ff2jf4oqm4ciqr",
    "xn__4kq52br32ac45b5cab363s",
    "xn__ehqu5ct80hk8j",
    "xn__zwqw6n152ck8j",
    "xn__zwq77gvzc90gforqm4ciqr",
    "xn__zwqw6nz3hcs0c5cab363s",
    "xn__dlqp2bt28ik8j",
    "xn__p5tq87dn1m",
    "xn__i8s3a",
    "xn__tlqz70d7me",
    "xn__jeyz61dtle",
    "xn__i8st76f"
  ],
  "columnUpdatedAt": 1734614288653,
  "columnWidthMap": {
    "xn__4kq52bf4ff2jf4oqm4ciqr": 141,
    "xn__4kq52br32ac45b5cab363s": 142,
    "xn__4kq52bt28ik8j": 98,
    "xn__4zq432hizksna": 111,
    "xn__4zq47ci76bsq0a": 128,
    "xn__dlqp2bt28ik8j": 98,
    "xn__ehqu5ct80hk8j": 100,
    "xn__i8s3a": 71.00000000000001,
    "xn__i8st76f": 65.99999999999999,
    "xn__jeyz61dtle": 81,
    "xn__kjv635bn9lmik": 191.1875,
    "xn__p5tq87dn1m": 89,
    "xn__tlqz70d7me": 82,
    "xn__zwq77g4sizzmcm7b": 122,
    "xn__zwq77gvzc90gforqm4ciqr": 143,
    "xn__zwqu88acr6akcab": 114,
    "xn__zwqw6n152ck8j": 97,
    "xn__zwqw83l": 75
  },
  "compactMode": "SHORT",
  "customIsLoading": false,
  "customIsLoadingValue": "",
  "defaultPageSize": 0,
  "defaultSelectedRowIndex": 0,
  "defaultSelectedRowIndices": [
    0
  ],
  "delimiter": ",",
  "dynamicBindingPathList": [
    {
      "key": "accentColor"
    },
    {
      "key": "tableData"
    },
    {
      "key": "primaryColumns.xn__eqr1se2n6x9a.computedValue"
    },
    {
      "key": "primaryColumns.rowIndex.computedValue"
    },
    {
      "key": "primaryColumns.xn__zwqw83l.computedValue"
    },
    {
      "key": "primaryColumns.xn__zwq77g4sizzmcm7b.computedValue"
    },
    {
      "key": "primaryColumns.xn__zwqu88acr6akcab.computedValue"
    },
    {
      "key": "primaryColumns.xn__4kq52bt28ik8j.computedValue"
    },
    {
      "key": "primaryColumns.xn__4kq52bf4ff2jf4oqm4ciqr.computedValue"
    },
    {
      "key": "primaryColumns.xn__4kq52br32ac45b5cab363s.computedValue"
    },
    {
      "key": "primaryColumns.xn__ehqu5ct80hk8j.computedValue"
    },
    {
      "key": "primaryColumns.xn__zwqw6n152ck8j.computedValue"
    },
    {
      "key": "primaryColumns.xn__zwq77gvzc90gforqm4ciqr.computedValue"
    },
    {
      "key": "primaryColumns.xn__zwqw6nz3hcs0c5cab363s.computedValue"
    },
    {
      "key": "primaryColumns.xn__dlqp2bt28ik8j.computedValue"
    },
    {
      "key": "primaryColumns.xn__p5tq87dn1m.computedValue"
    },
    {
      "key": "primaryColumns.xn__i8s3a.computedValue"
    },
    {
      "key": "primaryColumns.xn__tlqz70d7me.computedValue"
    },
    {
      "key": "primaryColumns.xn__jeyz61dtle.computedValue"
    },
    {
      "key": "primaryColumns.xn__i8st76f.computedValue"
    }
  ],
  "dynamicPropertyPathList": [
    {
      "key": "tableData"
    }
  ],
  "dynamicTriggerPathList": [
    {
      "key": "onRowSelected"
    }
  ],
  "enableClientSideSearch": true,
  "flexVerticalAlignment": "start",
  "fontStyle": "",
  "horizontalAlignment": "LEFT",
  "inlineEditingSaveOption": "ROW_LEVEL",
  "isLoading": false,
  "isSortable": true,
  "isVisible": true,
  "isVisibleDownload": false,
  "isVisibleFilters": false,
  "isVisiblePagination": true,
  "isVisibleSearch": true,
  "key": "566fehvagr",
  "label": "Data",
  "leftColumn": 0,
  "minWidth": 450,
  "mobileBottomRow": 51,
  "mobileLeftColumn": 1,
  "mobileRightColumn": 35,
  "mobileTopRow": 23,
  "needsErrorInfo": false,
  "onRowSelected": "{{showModal(Modal_user_log.name);}}",
  "originalBottomRow": 63,
  "originalTopRow": 10,
  "parentColumnSpace": 19.8125,
  "parentId": "ka0f9tcqmk",
  "parentRowSpace": 10,
  "primaryColumns": {
    "rowIndex": {
      "alias": "rowIndex",
      "allowCellWrapping": false,
      "allowSameOptionsInNewRow": true,
      "cellBackground": "",
      "columnType": "number",
      "computedValue": "{{(() => { const tableData = Table_pivot.processedTableData || []; return tableData.length > 0 ? tableData.map((currentRow, currentIndex) => ( currentRow[\"rowIndex\"])) :  currentRow[\"rowIndex\"] })()}}",
      "currencyCode": "USD",
      "decimals": 0,
      "enableFilter": true,
      "enableSort": true,
      "fontStyle": "",
      "horizontalAlignment": "LEFT",
      "id": "rowIndex",
      "index": 9,
      "isCellEditable": false,
      "isCellVisible": true,
      "isDerived": false,
      "isDisabled": false,
      "isDiscardVisible": true,
      "isEditable": false,
      "isSaveVisible": true,
      "isVisible": false,
      "label": "rowIndex",
      "notation": "standard",
      "originalId": "rowIndex",
      "sticky": "",
      "textColor": "",
      "textSize": "0.875rem",
      "thousandSeparator": true,
      "validation": {},
      "verticalAlignment": "CENTER",
      "width": 150
    },
    "xn__4kq52bf4ff2jf4oqm4ciqr": {
      "alias": "倫語二階同學會",
      "allowCellWrapping": false,
      "allowSameOptionsInNewRow": true,
      "cellBackground": "",
      "columnType": "text",
      "computedValue": "{{(() => { const tableData = Table_pivot.processedTableData || []; return tableData.length > 0 ? tableData.map((currentRow, currentIndex) => ( currentRow[\"倫語二階同學會\"])) :  currentRow[\"倫語二階同學會\"] })()}}",
      "currencyCode": "USD",
      "decimals": 0,
      "enableFilter": true,
      "enableSort": true,
      "fontStyle": "",
      "horizontalAlignment": "LEFT",
      "id": "xn__4kq52bf4ff2jf4oqm4ciqr",
      "index": 5,
      "isCellEditable": false,
      "isCellVisible": true,
      "isDerived": false,
      "isDisabled": false,
      "isDiscardVisible": true,
      "isEditable": false,
      "isSaveVisible": true,
      "isVisible": true,
      "label": "倫語二階同學會",
      "notation": "standard",
      "originalId": "倫語二階同學會",
      "sticky": "",
      "textColor": "",
      "textSize": "0.875rem",
      "thousandSeparator": true,
      "validation": {},
      "verticalAlignment": "CENTER",
      "width": 150
    },
    "xn__4kq52br32ac45b5cab363s": {
      "alias": "倫語二階課後課",
      "allowCellWrapping": false,
      "allowSameOptionsInNewRow": true,
      "cellBackground": "",
      "columnType": "text",
      "computedValue": "{{(() => { const tableData = Table_pivot.processedTableData || []; return tableData.length > 0 ? tableData.map((currentRow, currentIndex) => ( currentRow[\"倫語二階課後課\"])) :  currentRow[\"倫語二階課後課\"] })()}}",
      "currencyCode": "USD",
      "decimals": 0,
      "enableFilter": true,
      "enableSort": true,
      "fontStyle": "",
      "horizontalAlignment": "LEFT",
      "id": "xn__4kq52br32ac45b5cab363s",
      "index": 6,
      "isCellEditable": false,
      "isCellVisible": true,
      "isDerived": false,
      "isDisabled": false,
      "isDiscardVisible": true,
      "isEditable": false,
      "isSaveVisible": true,
      "isVisible": true,
      "label": "倫語二階課後課",
      "notation": "standard",
      "originalId": "倫語二階課後課",
      "sticky": "",
      "textColor": "",
      "textSize": "0.875rem",
      "thousandSeparator": true,
      "validation": {},
      "verticalAlignment": "CENTER",
      "width": 150
    },
    "xn__4kq52bt28ik8j": {
      "alias": "倫語二階",
      "allowCellWrapping": false,
      "allowSameOptionsInNewRow": true,
      "cellBackground": "",
      "columnType": "number",
      "computedValue": "{{(() => { const tableData = Table_pivot.processedTableData || []; return tableData.length > 0 ? tableData.map((currentRow, currentIndex) => ( currentRow[\"倫語二階\"])) :  currentRow[\"倫語二階\"] })()}}",
      "currencyCode": "USD",
      "decimals": 0,
      "enableFilter": true,
      "enableSort": true,
      "fontStyle": "",
      "horizontalAlignment": "LEFT",
      "id": "xn__4kq52bt28ik8j",
      "index": 4,
      "isCellEditable": false,
      "isCellVisible": true,
      "isDerived": false,
      "isDisabled": false,
      "isDiscardVisible": true,
      "isEditable": false,
      "isSaveVisible": true,
      "isVisible": true,
      "label": "倫語二階",
      "notation": "standard",
      "originalId": "倫語二階",
      "sticky": "",
      "textColor": "",
      "textSize": "0.875rem",
      "thousandSeparator": true,
      "validation": {},
      "verticalAlignment": "CENTER",
      "width": 150
    },
    "xn__dlqp2bt28ik8j": {
      "alias": "倫語五階",
      "allowCellWrapping": false,
      "allowSameOptionsInNewRow": true,
      "cellBackground": "",
      "columnType": "text",
      "computedValue": "{{(() => { const tableData = Table_pivot.processedTableData || []; return tableData.length > 0 ? tableData.map((currentRow, currentIndex) => ( currentRow[\"倫語五階\"])) :  currentRow[\"倫語五階\"] })()}}",
      "currencyCode": "USD",
      "decimals": 0,
      "enableFilter": true,
      "enableSort": true,
      "fontStyle": "",
      "horizontalAlignment": "LEFT",
      "id": "xn__dlqp2bt28ik8j",
      "index": 11,
      "isCellEditable": false,
      "isCellVisible": true,
      "isDerived": false,
      "isDisabled": false,
      "isDiscardVisible": true,
      "isEditable": false,
      "isSaveVisible": true,
      "isVisible": true,
      "label": "倫語五階",
      "notation": "standard",
      "originalId": "倫語五階",
      "sticky": "",
      "textColor": "",
      "textSize": "0.875rem",
      "thousandSeparator": true,
      "validation": {},
      "verticalAlignment": "CENTER",
      "width": 150
    },
    "xn__ehqu5ct80hk8j": {
      "alias": "倫語三階",
      "allowCellWrapping": false,
      "allowSameOptionsInNewRow": true,
      "cellBackground": "",
      "columnType": "number",
      "computedValue": "{{(() => { const tableData = Table_pivot.processedTableData || []; return tableData.length > 0 ? tableData.map((currentRow, currentIndex) => ( currentRow[\"倫語三階\"])) :  currentRow[\"倫語三階\"] })()}}",
      "currencyCode": "USD",
      "decimals": 0,
      "enableFilter": true,
      "enableSort": true,
      "fontStyle": "",
      "horizontalAlignment": "LEFT",
      "id": "xn__ehqu5ct80hk8j",
      "index": 7,
      "isCellEditable": false,
      "isCellVisible": true,
      "isDerived": false,
      "isDisabled": false,
      "isDiscardVisible": true,
      "isEditable": false,
      "isSaveVisible": true,
      "isVisible": true,
      "label": "倫語三階",
      "notation": "standard",
      "originalId": "倫語三階",
      "sticky": "",
      "textColor": "",
      "textSize": "0.875rem",
      "thousandSeparator": true,
      "validation": {},
      "verticalAlignment": "CENTER",
      "width": 150
    },
    "xn__eqr1se2n6x9a": {
      "alias": "學員名稱",
      "allowCellWrapping": false,
      "allowSameOptionsInNewRow": true,
      "cellBackground": "",
      "columnType": "text",
      "computedValue": "{{(() => { const tableData = Table_pivot.processedTableData || []; return tableData.length > 0 ? tableData.map((currentRow, currentIndex) => ( currentRow[\"學員名稱\"])) :  currentRow[\"學員名稱\"] })()}}",
      "currencyCode": "USD",
      "decimals": 0,
      "enableFilter": true,
      "enableSort": true,
      "fontStyle": "",
      "horizontalAlignment": "LEFT",
      "id": "xn__eqr1se2n6x9a",
      "index": 0,
      "isCellEditable": false,
      "isCellVisible": true,
      "isDerived": false,
      "isDisabled": false,
      "isDiscardVisible": true,
      "isEditable": false,
      "isSaveVisible": true,
      "isVisible": true,
      "label": "學員名稱",
      "notation": "standard",
      "originalId": "學員名稱",
      "sticky": "",
      "textColor": "",
      "textSize": "0.875rem",
      "thousandSeparator": true,
      "validation": {},
      "verticalAlignment": "CENTER",
      "width": 150
    },
    "xn__i8s3a": {
      "alias": "孟子",
      "allowCellWrapping": false,
      "allowSameOptionsInNewRow": true,
      "cellBackground": "",
      "columnType": "text",
      "computedValue": "{{(() => { const tableData = Table_pivot.processedTableData || []; return tableData.length > 0 ? tableData.map((currentRow, currentIndex) => ( currentRow[\"孟子\"])) :  currentRow[\"孟子\"] })()}}",
      "currencyCode": "USD",
      "decimals": 0,
      "enableFilter": true,
      "enableSort": true,
      "fontStyle": "",
      "horizontalAlignment": "LEFT",
      "id": "xn__i8s3a",
      "index": 13,
      "isCellEditable": false,
      "isCellVisible": true,
      "isDerived": false,
      "isDisabled": false,
      "isDiscardVisible": true,
      "isEditable": false,
      "isSaveVisible": true,
      "isVisible": true,
      "label": "孟子",
      "notation": "standard",
      "originalId": "孟子",
      "sticky": "",
      "textColor": "",
      "textSize": "0.875rem",
      "thousandSeparator": true,
      "validation": {},
      "verticalAlignment": "CENTER",
      "width": 150
    },
    "xn__i8st76f": {
      "alias": "老子",
      "allowCellWrapping": false,
      "allowSameOptionsInNewRow": true,
      "cellBackground": "",
      "columnType": "text",
      "computedValue": "{{(() => { const tableData = Table_pivot.processedTableData || []; return tableData.length > 0 ? tableData.map((currentRow, currentIndex) => ( currentRow[\"老子\"])) :  currentRow[\"老子\"] })()}}",
      "currencyCode": "USD",
      "decimals": 0,
      "enableFilter": true,
      "enableSort": true,
      "fontStyle": "",
      "horizontalAlignment": "LEFT",
      "id": "xn__i8st76f",
      "index": 16,
      "isCellEditable": false,
      "isCellVisible": true,
      "isDerived": false,
      "isDisabled": false,
      "isDiscardVisible": true,
      "isEditable": false,
      "isSaveVisible": true,
      "isVisible": true,
      "label": "老子",
      "notation": "standard",
      "originalId": "老子",
      "sticky": "",
      "textColor": "",
      "textSize": "0.875rem",
      "thousandSeparator": true,
      "validation": {},
      "verticalAlignment": "CENTER",
      "width": 150
    },
    "xn__jeyz61dtle": {
      "alias": "進階班",
      "allowCellWrapping": false,
      "allowSameOptionsInNewRow": true,
      "cellBackground": "",
      "columnType": "text",
      "computedValue": "{{(() => { const tableData = Table_pivot.processedTableData || []; return tableData.length > 0 ? tableData.map((currentRow, currentIndex) => ( currentRow[\"進階班\"])) :  currentRow[\"進階班\"] })()}}",
      "currencyCode": "USD",
      "decimals": 0,
      "enableFilter": true,
      "enableSort": true,
      "fontStyle": "",
      "horizontalAlignment": "LEFT",
      "id": "xn__jeyz61dtle",
      "index": 15,
      "isCellEditable": false,
      "isCellVisible": true,
      "isDerived": false,
      "isDisabled": false,
      "isDiscardVisible": true,
      "isEditable": false,
      "isSaveVisible": true,
      "isVisible": true,
      "label": "進階班",
      "notation": "standard",
      "originalId": "進階班",
      "sticky": "",
      "textColor": "",
      "textSize": "0.875rem",
      "thousandSeparator": true,
      "validation": {},
      "verticalAlignment": "CENTER",
      "width": 150
    },
    "xn__p5tq87dn1m": {
      "alias": "道德經",
      "allowCellWrapping": false,
      "allowSameOptionsInNewRow": true,
      "cellBackground": "",
      "columnType": "text",
      "computedValue": "{{(() => { const tableData = Table_pivot.processedTableData || []; return tableData.length > 0 ? tableData.map((currentRow, currentIndex) => ( currentRow[\"道德經\"])) :  currentRow[\"道德經\"] })()}}",
      "currencyCode": "USD",
      "decimals": 0,
      "enableFilter": true,
      "enableSort": true,
      "fontStyle": "",
      "horizontalAlignment": "LEFT",
      "id": "xn__p5tq87dn1m",
      "index": 12,
      "isCellEditable": false,
      "isCellVisible": true,
      "isDerived": false,
      "isDisabled": false,
      "isDiscardVisible": true,
      "isEditable": false,
      "isSaveVisible": true,
      "isVisible": true,
      "label": "道德經",
      "notation": "standard",
      "originalId": "道德經",
      "sticky": "",
      "textColor": "",
      "textSize": "0.875rem",
      "thousandSeparator": true,
      "validation": {},
      "verticalAlignment": "CENTER",
      "width": 150
    },
    "xn__tlqz70d7me": {
      "alias": "交流會",
      "allowCellWrapping": false,
      "allowSameOptionsInNewRow": true,
      "cellBackground": "",
      "columnType": "text",
      "computedValue": "{{(() => { const tableData = Table_pivot.processedTableData || []; return tableData.length > 0 ? tableData.map((currentRow, currentIndex) => ( currentRow[\"交流會\"])) :  currentRow[\"交流會\"] })()}}",
      "currencyCode": "USD",
      "decimals": 0,
      "enableFilter": true,
      "enableSort": true,
      "fontStyle": "",
      "horizontalAlignment": "LEFT",
      "id": "xn__tlqz70d7me",
      "index": 14,
      "isCellEditable": false,
      "isCellVisible": true,
      "isDerived": false,
      "isDisabled": false,
      "isDiscardVisible": true,
      "isEditable": false,
      "isSaveVisible": true,
      "isVisible": true,
      "label": "交流會",
      "notation": "standard",
      "originalId": "交流會",
      "sticky": "",
      "textColor": "",
      "textSize": "0.875rem",
      "thousandSeparator": true,
      "validation": {},
      "verticalAlignment": "CENTER",
      "width": 150
    },
    "xn__zwq77g4sizzmcm7b": {
      "alias": "倫語同學會",
      "allowCellWrapping": false,
      "allowSameOptionsInNewRow": true,
      "cellBackground": "",
      "columnType": "text",
      "computedValue": "{{(() => { const tableData = Table_pivot.processedTableData || []; return tableData.length > 0 ? tableData.map((currentRow, currentIndex) => ( currentRow[\"倫語同學會\"])) :  currentRow[\"倫語同學會\"] })()}}",
      "currencyCode": "USD",
      "decimals": 0,
      "enableFilter": true,
      "enableSort": true,
      "fontStyle": "",
      "horizontalAlignment": "LEFT",
      "id": "xn__zwq77g4sizzmcm7b",
      "index": 2,
      "isCellEditable": false,
      "isCellVisible": true,
      "isDerived": false,
      "isDisabled": false,
      "isDiscardVisible": true,
      "isEditable": false,
      "isSaveVisible": true,
      "isVisible": true,
      "label": "倫語同學會",
      "notation": "standard",
      "originalId": "倫語同學會",
      "sticky": "",
      "textColor": "",
      "textSize": "0.875rem",
      "thousandSeparator": true,
      "validation": {},
      "verticalAlignment": "CENTER",
      "width": 150
    },
    "xn__zwq77gvzc90gforqm4ciqr": {
      "alias": "倫語四階同學會",
      "allowCellWrapping": false,
      "allowSameOptionsInNewRow": true,
      "cellBackground": "",
      "columnType": "text",
      "computedValue": "{{(() => { const tableData = Table_pivot.processedTableData || []; return tableData.length > 0 ? tableData.map((currentRow, currentIndex) => ( currentRow[\"倫語四階同學會\"])) :  currentRow[\"倫語四階同學會\"] })()}}",
      "currencyCode": "USD",
      "decimals": 0,
      "enableFilter": true,
      "enableSort": true,
      "fontStyle": "",
      "horizontalAlignment": "LEFT",
      "id": "xn__zwq77gvzc90gforqm4ciqr",
      "index": 9,
      "isCellEditable": false,
      "isCellVisible": true,
      "isDerived": false,
      "isDisabled": false,
      "isDiscardVisible": true,
      "isEditable": false,
      "isSaveVisible": true,
      "isVisible": true,
      "label": "倫語四階同學會",
      "notation": "standard",
      "originalId": "倫語四階同學會",
      "sticky": "",
      "textColor": "",
      "textSize": "0.875rem",
      "thousandSeparator": true,
      "validation": {},
      "verticalAlignment": "CENTER",
      "width": 150
    },
    "xn__zwqu88acr6akcab": {
      "alias": "倫語課後課",
      "allowCellWrapping": false,
      "allowSameOptionsInNewRow": true,
      "cellBackground": "",
      "columnType": "text",
      "computedValue": "{{(() => { const tableData = Table_pivot.processedTableData || []; return tableData.length > 0 ? tableData.map((currentRow, currentIndex) => ( currentRow[\"倫語課後課\"])) :  currentRow[\"倫語課後課\"] })()}}",
      "currencyCode": "USD",
      "decimals": 0,
      "enableFilter": true,
      "enableSort": true,
      "fontStyle": "",
      "horizontalAlignment": "LEFT",
      "id": "xn__zwqu88acr6akcab",
      "index": 3,
      "isCellEditable": false,
      "isCellVisible": true,
      "isDerived": false,
      "isDisabled": false,
      "isDiscardVisible": true,
      "isEditable": false,
      "isSaveVisible": true,
      "isVisible": true,
      "label": "倫語課後課",
      "notation": "standard",
      "originalId": "倫語課後課",
      "sticky": "",
      "textColor": "",
      "textSize": "0.875rem",
      "thousandSeparator": true,
      "validation": {},
      "verticalAlignment": "CENTER",
      "width": 150
    },
    "xn__zwqw6n152ck8j": {
      "alias": "倫語四階",
      "allowCellWrapping": false,
      "allowSameOptionsInNewRow": true,
      "cellBackground": "",
      "columnType": "text",
      "computedValue": "{{(() => { const tableData = Table_pivot.processedTableData || []; return tableData.length > 0 ? tableData.map((currentRow, currentIndex) => ( currentRow[\"倫語四階\"])) :  currentRow[\"倫語四階\"] })()}}",
      "currencyCode": "USD",
      "decimals": 0,
      "enableFilter": true,
      "enableSort": true,
      "fontStyle": "",
      "horizontalAlignment": "LEFT",
      "id": "xn__zwqw6n152ck8j",
      "index": 8,
      "isCellEditable": false,
      "isCellVisible": true,
      "isDerived": false,
      "isDisabled": false,
      "isDiscardVisible": true,
      "isEditable": false,
      "isSaveVisible": true,
      "isVisible": true,
      "label": "倫語四階",
      "notation": "standard",
      "originalId": "倫語四階",
      "sticky": "",
      "textColor": "",
      "textSize": "0.875rem",
      "thousandSeparator": true,
      "validation": {},
      "verticalAlignment": "CENTER",
      "width": 150
    },
    "xn__zwqw6nz3hcs0c5cab363s": {
      "alias": "倫語四階課後課",
      "allowCellWrapping": false,
      "allowSameOptionsInNewRow": true,
      "cellBackground": "",
      "columnType": "text",
      "computedValue": "{{(() => { const tableData = Table_pivot.processedTableData || []; return tableData.length > 0 ? tableData.map((currentRow, currentIndex) => ( currentRow[\"倫語四階課後課\"])) :  currentRow[\"倫語四階課後課\"] })()}}",
      "currencyCode": "USD",
      "decimals": 0,
      "enableFilter": true,
      "enableSort": true,
      "fontStyle": "",
      "horizontalAlignment": "LEFT",
      "id": "xn__zwqw6nz3hcs0c5cab363s",
      "index": 10,
      "isCellEditable": false,
      "isCellVisible": true,
      "isDerived": false,
      "isDisabled": false,
      "isDiscardVisible": true,
      "isEditable": false,
      "isSaveVisible": true,
      "isVisible": true,
      "label": "倫語四階課後課",
      "notation": "standard",
      "originalId": "倫語四階課後課",
      "sticky": "",
      "textColor": "",
      "textSize": "0.875rem",
      "thousandSeparator": true,
      "validation": {},
      "verticalAlignment": "CENTER",
      "width": 150
    },
    "xn__zwqw83l": {
      "alias": "倫語",
      "allowCellWrapping": false,
      "allowSameOptionsInNewRow": true,
      "cellBackground": "",
      "columnType": "number",
      "computedValue": "{{(() => { const tableData = Table_pivot.processedTableData || []; return tableData.length > 0 ? tableData.map((currentRow, currentIndex) => ( currentRow[\"倫語\"])) :  currentRow[\"倫語\"] })()}}",
      "currencyCode": "USD",
      "decimals": 0,
      "enableFilter": true,
      "enableSort": true,
      "fontStyle": "",
      "horizontalAlignment": "LEFT",
      "id": "xn__zwqw83l",
      "index": 1,
      "isCellEditable": false,
      "isCellVisible": true,
      "isDerived": false,
      "isDisabled": false,
      "isDiscardVisible": true,
      "isEditable": false,
      "isSaveVisible": true,
      "isVisible": true,
      "label": "倫語",
      "notation": "standard",
      "originalId": "倫語",
      "sticky": "",
      "textColor": "",
      "textSize": "0.875rem",
      "thousandSeparator": true,
      "validation": {},
      "verticalAlignment": "CENTER",
      "width": 150
    }
  },
  "renderMode": "CANVAS",
  "responsiveBehavior": "fill",
  "rightColumn": 64,
  "searchKey": "",
  "tableData": "{{filter.filtered_logs_pivot}}",
  "textSize": "0.875rem",
  "topRow": 4,
  "totalRecordsCount": 0,
  "type": "TABLE_WIDGET_V2",
  "version": 2,
  "verticalAlignment": "CENTER",
  "widgetId": "zyr1n8vr37",
  "widgetName": "Table_pivot"
}